{
    "type": "postgres",
    "host": "postgres_database",
    "port": 5432,
    "username": "biko",
    "password": "240063013",
    "database": "biko_mechanic",
    "synchronize": false,
    "logging": true,
    "entities": ["src/database/entities/**/*.ts"],
    "migrations": ["src/database/migrations/**/*.ts"],
    "subscribers": ["src/database/subscribers/**/*.ts"],
    "cli": {
        "entitiesDir": "src/database/entities",
        "migrationsDir": "src/database/migrations",
        "subscribersDir": "src/database/subscribers"
    }
}
